pycoder/__init__.py
pycoder/__main__.py
pycoder/config.py
pycoder/imports.py
pycoder/utils.py
pycoder/version.py
pycoder/api/__init__.py
pycoder/api/app.py
pycoder/api/cli.py
pycoder/api/index.html
pycoder/api/main.py
pycoder/data/__init__.py
pycoder/data/classes.py
pycoder/data/download.py
pycoder/data/modules.py
pycoder/data/processing.py
pycoder/model/__init__.py
pycoder/model/inference.py
pycoder/model/trainer.py
pycoder/model/training.py
pycoder/model/transformer.py
pycoder-1.2.4.dist-info/LICENSE
pycoder-1.2.4.dist-info/METADATA
pycoder-1.2.4.dist-info/WHEEL
pycoder-1.2.4.dist-info/entry_points.txt
pycoder-1.2.4.dist-info/top_level.txt
pycoder-1.2.4.dist-info/RECORD
