Metadata-Version: 2.1
Name: pycoder
Version: 1.2.4
Summary: A package to generate Python code from given topics and description
Home-page: https://github.com/himanshu-dutta/pycoder
Author: Himanshu Dutta
Author-email: meet.himanshu.dutta@gmail.com
License: MIT License
Platform: linux
Platform: unix
Classifier: Programming Language :: Python :: 3.7
Classifier: Programming Language :: Python :: 3.8
Classifier: Programming Language :: Python :: 3.9
Classifier: License :: OSI Approved :: MIT License
Classifier: Operating System :: OS Independent
Requires-Python: >3.7
Requires-Dist: torch (>=1.8.1)
Requires-Dist: typer (==0.3.2)
Requires-Dist: transformers (==4.6.1)
Requires-Dist: markdown (==3.3.4)
Requires-Dist: fastapi (==0.65.1)
Requires-Dist: uvicorn (==0.13.4)
Requires-Dist: pygments (==2.9.0)
Requires-Dist: click-spinner (==0.1.10)
Provides-Extra: dev
Requires-Dist: pytest ; extra == 'dev'
Requires-Dist: black ; extra == 'dev'
Requires-Dist: wandb ; extra == 'dev'
Requires-Dist: pygithub ; extra == 'dev'
